vocos/__init__.py
vocos/dataset.py
vocos/discriminators.py
vocos/experiment.py
vocos/feature_extractors.py
vocos/heads.py
vocos/helpers.py
vocos/loss.py
vocos/models.py
vocos/modules.py
vocos/pretrained.py
vocos/spectral_ops.py
vocos-0.0.4.dist-info/LICENSE
vocos-0.0.4.dist-info/METADATA
vocos-0.0.4.dist-info/WHEEL
vocos-0.0.4.dist-info/top_level.txt
vocos-0.0.4.dist-info/RECORD
