Metadata-Version: 2.1
Name: vocos
Version: 0.0.4
Summary: Fourier-based neural vocoder for high-quality audio synthesis
Home-page: https://github.com/charactr-platform/vocos
Author: Hubert Siuzdak
Author-email: huberts@charactr.com
License-File: LICENSE
Requires-Dist: torch
Requires-Dist: torchaudio
Requires-Dist: numpy
Requires-Dist: scipy
Requires-Dist: einops
Requires-Dist: pyyaml
Requires-Dist: huggingface-hub
Requires-Dist: encodec ==0.1.1
Provides-Extra: train
Requires-Dist: pytorch-lightning ==1.8.6 ; extra == 'train'
Requires-Dist: jsonargparse[signatures] ; extra == 'train'
Requires-Dist: transformers ; extra == 'train'
Requires-Dist: matplotlib ; extra == 'train'
Requires-Dist: torchcrepe ; extra == 'train'
Requires-Dist: pesq ; extra == 'train'
Requires-Dist: fairseq ; extra == 'train'
